splatnet/__init__.py
splatnet/splatnet2/__init__.py
splatnet/splatnet2/config.py
splatnet/splatnet2/models.py
splatnet/splatnet2/splatnet2.py
splatnet-0.1.5.dist-info/LICENSE
splatnet-0.1.5.dist-info/WHEEL
splatnet-0.1.5.dist-info/METADATA
splatnet-0.1.5.dist-info/RECORD
