Metadata-Version: 2.1
Name: splatnet
Version: 0.1.5
Summary: Wrapper for Splatnet (Splatoon API)
Home-page: https://github.com/unatoon/splatnet
License: MIT
Author: unatoon
Author-email: unatoon@users.noreply.github.com
Requires-Python: >=3.10,<4.0
Classifier: License :: OSI Approved :: MIT License
Classifier: Programming Language :: Python :: 3
Classifier: Programming Language :: Python :: 3.10
Requires-Dist: beautifulsoup4 (>=4.11.1,<5.0.0)
Requires-Dist: pydantic (>=1.9.0,<2.0.0)
Requires-Dist: requests (>=2.27.1,<3.0.0)
Project-URL: Documentation, https://github.com/unatoon/splatnet
Project-URL: Repository, https://github.com/unatoon/splatnet
